src/__init__.py
src/core/__init__.py
src/core/engine.py
pytobf-1.0.1.dist-info/METADATA
pytobf-1.0.1.dist-info/WHEEL
pytobf-1.0.1.dist-info/entry_points.txt
pytobf-1.0.1.dist-info/top_level.txt
pytobf-1.0.1.dist-info/RECORD
