Metadata-Version: 2.4
Name: pytobf
Version: 1.0.1
Summary: The sacred Python to Brainfuck transpiler
Author: MurilooPrDev
Requires-Python: >=3.6
Dynamic: author
Dynamic: description
Dynamic: description-content-type
Dynamic: requires-python
Dynamic: summary
